{
  "app": {
    "base_language": "en",
    "push": {
      "source": [
        {
          "path": "./GitHub-DEV-main/CSV/en/countries.csv",
          "file_format": "csv",
          "tag": "country.csv",
          "columnDescription": {
            "KEY": 0,
            "en": 1
          },
          "excludeHeaderRow": true,
          "key_prefix": "country_",
          "language": "en"
        },
        {
          "path": "./GitHub-DEV-main/CSV/en/payments.csv",
          "file_format": "csv",
          "tag": "app:language.csv",
          "columnDescription": {
            "KEY": 0,
            "en": 1
          },
          "excludeHeaderRow": true,
          "language": "en"
        }
      ]
    },
    "pull": {
      "target": [
        {
          "path": "./GitHub-DEV-main/CSV/en/<language>.csv",
          "file_format": "csv",
          "tag": "country.csv",
          "columnDescription": {
            "KEY": 0,
            "<language>": 1
          },
          "key_prefix": "country_",
          "exclude_languages": [
            "en"
          ]
        },
        {
          "path": "./GitHub-DEV-main/CSV/en/<language>.csv",
          "file_format": "csv",
          "tag": "app:language.csv",
          "excludeHeaderRow": true,
          "excludeBaseLang": true,
          "columnDescription": {
            "KEY": 0,
            "<language>": 1
          },
          "exclude_languages": [
            "en"
          ]
        }
      ]
    }
  }
}